{
    "ordering": [
        [
            "A1"
        ]
    ],
    "brand": {
        "brand": "polyelectric",
        "brandId": []
    },
    "metadata": {
        "displayName": "Polyetric_bin",
        "displayCategory": "reservoir",
        "displayVolumeUnits": "µL",
        "tags": []
    },
    "dimensions": {
        "xDimension": 127.5,
        "yDimension": 85.5,
        "zDimension": 70
    },
    "wells": {
        "A1": {
            "depth": 60,
            "totalLiquidVolume": 100000,
            "shape": "rectangular",
            "xDimension": 120,
            "yDimension": 70,
            "x": 64,
            "y": 43.5,
            "z": 10
        }
    },
    "groups": [
        {
            "metadata": {
                "wellBottomShape": "flat"
            },
            "wells": [
                "A1"
            ]
        }
    ],
    "parameters": {
        "format": "irregular",
        "quirks": [
            "centerMultichannelOnWells",
            "touchTipDisabled"
        ],
        "isTiprack": false,
        "isMagneticModuleCompatible": false,
        "loadName": "pe_trash"
    },
    "namespace": "custom_beta",
    "version": 1,
    "schemaVersion": 2,
    "cornerOffsetFromSlot": {
        "x": 0,
        "y": 0,
        "z": 0
    }
}